pyminesweeper/__init__.py
pyminesweeper/libminesweeper.dll
pyminesweeper/libminesweeper.so
pyminesweeper/minesweeper.py
py_minesweeper-1.5.0.dist-info/METADATA
py_minesweeper-1.5.0.dist-info/WHEEL
py_minesweeper-1.5.0.dist-info/top_level.txt
py_minesweeper-1.5.0.dist-info/RECORD
