Metadata-Version: 2.1
Name: py-minesweeper
Version: 1.5.0
Summary: Minesweeper engine for python
Home-page: UNKNOWN
Author: Tekcno
Author-email: tekcno@tekcno.com
License: UNKNOWN
Platform: UNKNOWN
Classifier: Development Status :: 3 - Alpha
Classifier: Topic :: Utilities
